Buffer.v
// Buffer.v
// use generate

module Buffer #(
    parameter SYSTOLIC_SIZE = 8,
    parameter ACTIVATION_WIDTH = 8
) (
    input clk,
    input rst_n,
    input test_mode,    // 0: 正常模式45度, 1: 測試模式平行送入
    input [SYSTOLIC_SIZE*ACTIVATION_WIDTH-1:0] activation_in_flat,

    output [SYSTOLIC_SIZE*ACTIVATION_WIDTH-1:0] activation_out_flat
);

    // 動態分解輸入數據
    wire [ACTIVATION_WIDTH-1:0] activation_in [0:SYSTOLIC_SIZE-1];
    wire [ACTIVATION_WIDTH-1:0] activation_out [0:SYSTOLIC_SIZE-1];
    
    genvar k;
    generate
        for (k = 0; k < SYSTOLIC_SIZE; k = k + 1) begin : in_out_split
            assign activation_in[k] = activation_in_flat[k*ACTIVATION_WIDTH +: ACTIVATION_WIDTH];
            assign activation_out_flat[k*ACTIVATION_WIDTH +: ACTIVATION_WIDTH] = activation_out[k];
        end
    endgenerate

    // Row 0: 直接輸出，沒有registers
    assign activation_out[0] = activation_in[0];

    // Row 1 到 Row (SYSTOLIC_SIZE-1): 每行宣告所需數量的registers
    genvar i;
    integer j;
    generate
        for (i = 1; i < SYSTOLIC_SIZE; i = i + 1) begin : row_gen
            // 第i行需要i個registers
            reg [ACTIVATION_WIDTH-1:0] shift_regs [0:i-1];
            
            // Shift register邏輯
            always @(posedge clk or negedge rst_n) begin
                if (!rst_n) begin
                    // 重置該行的所有registers
                    for (j = 0; j < i; j = j + 1) begin
                        shift_regs[j] <= {ACTIVATION_WIDTH{1'b0}};
                    end
                end else begin
                    // 輸入到第一個register
                    shift_regs[0] <= activation_in[i];
                    
                    // Shift register操作：從第二個開始
                    for (j = 1; j < i; j = j + 1) begin
                        shift_regs[j] <= shift_regs[j-1];
                    end
                end
            end
            
            // 輸出選擇：根據test_mode決定
            assign activation_out[i] = test_mode ? activation_in[i] : shift_regs[i-1];
        end
    endgenerate

endmodule


// // Buffer.v
// // 爆開

// module Buffer #(
//     parameter SYSTOLIC_SIZE = 8,  // 可設定的脈動陣列大小，預設為8x8
//     parameter ACTIVATION_WIDTH = 8
// ) (
//     input clk,
//     input rst_n,
//     input test_mode,    // 0: 正常模式45度, 1: 測試模式平行送入
//     input [SYSTOLIC_SIZE*ACTIVATION_WIDTH-1:0] activation_in_flat,
//     output [ACTIVATION_WIDTH-1:0] activation_out [0:SYSTOLIC_SIZE-1]
// );

//     wire [ACTIVATION_WIDTH-1:0] activation_in [0:SYSTOLIC_SIZE-1];

//     assign activation_in[0] = activation_in_flat[0*ACTIVATION_WIDTH +: ACTIVATION_WIDTH];
//     assign activation_in[1] = activation_in_flat[1*ACTIVATION_WIDTH +: ACTIVATION_WIDTH];
//     assign activation_in[2] = activation_in_flat[2*ACTIVATION_WIDTH +: ACTIVATION_WIDTH];
//     assign activation_in[3] = activation_in_flat[3*ACTIVATION_WIDTH +: ACTIVATION_WIDTH];
//     assign activation_in[4] = activation_in_flat[4*ACTIVATION_WIDTH +: ACTIVATION_WIDTH];
//     assign activation_in[5] = activation_in_flat[5*ACTIVATION_WIDTH +: ACTIVATION_WIDTH];
//     assign activation_in[6] = activation_in_flat[6*ACTIVATION_WIDTH +: ACTIVATION_WIDTH];
//     assign activation_in[7] = activation_in_flat[7*ACTIVATION_WIDTH +: ACTIVATION_WIDTH];

//     reg [ACTIVATION_WIDTH-1:0] reg_row1_0;
//     reg [ACTIVATION_WIDTH-1:0] reg_row2_0,reg_row2_1;
//     reg [ACTIVATION_WIDTH-1:0] reg_row3_0,reg_row3_1,reg_row3_2;
//     reg [ACTIVATION_WIDTH-1:0] reg_row4_0,reg_row4_1,reg_row4_2,reg_row4_3;
//     reg [ACTIVATION_WIDTH-1:0] reg_row5_0,reg_row5_1,reg_row5_2,reg_row5_3,reg_row5_4;
//     reg [ACTIVATION_WIDTH-1:0] reg_row6_0,reg_row6_1,reg_row6_2,reg_row6_3,reg_row6_4,reg_row6_5;
//     reg [ACTIVATION_WIDTH-1:0] reg_row7_0,reg_row7_1,reg_row7_2,reg_row7_3,reg_row7_4,reg_row7_5,reg_row7_6;


//     always @(posedge clk or negedge rst_n) begin
//         if (!rst_n) begin
//             reg_row1_0 <= {ACTIVATION_WIDTH{1'b0}};
//             reg_row2_0 <= {ACTIVATION_WIDTH{1'b0}}; reg_row2_1 <= {ACTIVATION_WIDTH{1'b0}};
//             reg_row3_0 <= {ACTIVATION_WIDTH{1'b0}}; reg_row3_1 <= {ACTIVATION_WIDTH{1'b0}}; reg_row3_2 <= {ACTIVATION_WIDTH{1'b0}};
//             reg_row4_0 <= {ACTIVATION_WIDTH{1'b0}}; reg_row4_1 <= {ACTIVATION_WIDTH{1'b0}}; reg_row4_2 <= {ACTIVATION_WIDTH{1'b0}}; reg_row4_3 <= {ACTIVATION_WIDTH{1'b0}};
//             reg_row5_0 <= {ACTIVATION_WIDTH{1'b0}}; reg_row5_1 <= {ACTIVATION_WIDTH{1'b0}}; reg_row5_2 <= {ACTIVATION_WIDTH{1'b0}}; reg_row5_3 <= {ACTIVATION_WIDTH{1'b0}}; reg_row5_4 <= {ACTIVATION_WIDTH{1'b0}};
//             reg_row6_0 <= {ACTIVATION_WIDTH{1'b0}}; reg_row6_1 <= {ACTIVATION_WIDTH{1'b0}}; reg_row6_2 <= {ACTIVATION_WIDTH{1'b0}}; reg_row6_3 <= {ACTIVATION_WIDTH{1'b0}}; reg_row6_4 <= {ACTIVATION_WIDTH{1'b0}}; reg_row6_5 <= {ACTIVATION_WIDTH{1'b0}};
//             reg_row7_0 <= {ACTIVATION_WIDTH{1'b0}}; reg_row7_1 <= {ACTIVATION_WIDTH{1'b0}}; reg_row7_2 <= {ACTIVATION_WIDTH{1'b0}}; reg_row7_3 <= {ACTIVATION_WIDTH{1'b0}}; reg_row7_4 <= {ACTIVATION_WIDTH{1'b0}}; reg_row7_5 <= {ACTIVATION_WIDTH{1'b0}}; reg_row7_6 <= {ACTIVATION_WIDTH{1'b0}};
//         end else begin
//             reg_row1_0 <= activation_in[1];
//             reg_row2_0 <= activation_in[2]; reg_row2_1 <= reg_row2_0;
//             reg_row3_0 <= activation_in[3]; reg_row3_1 <= reg_row3_0; reg_row3_2 <= reg_row3_1;
//             reg_row4_0 <= activation_in[4]; reg_row4_1 <= reg_row4_0; reg_row4_2 <= reg_row4_1; reg_row4_3 <= reg_row4_2;
//             reg_row5_0 <= activation_in[5]; reg_row5_1 <= reg_row5_0; reg_row5_2 <= reg_row5_1; reg_row5_3 <= reg_row5_2; reg_row5_4 <= reg_row5_3;
//             reg_row6_0 <= activation_in[6]; reg_row6_1 <= reg_row6_0; reg_row6_2 <= reg_row6_1; reg_row6_3 <= reg_row6_2; reg_row6_4 <= reg_row6_3; reg_row6_5 <= reg_row6_4;
//             reg_row7_0 <= activation_in[7]; reg_row7_1 <= reg_row7_0; reg_row7_2 <= reg_row7_1; reg_row7_3 <= reg_row7_2; reg_row7_4 <= reg_row7_3; reg_row7_5 <= reg_row7_4; reg_row7_6 <= reg_row7_5;
//         end
//     end
    
//     assign activation_out[0] = activation_in[0];
//     assign activation_out[1] = test_mode ? activation_in[1] : reg_row1_0 ;
//     assign activation_out[2] = test_mode ? activation_in[2] : reg_row2_1 ;    
//     assign activation_out[3] = test_mode ? activation_in[3] : reg_row3_2 ;
//     assign activation_out[4] = test_mode ? activation_in[4] : reg_row4_3 ;
//     assign activation_out[5] = test_mode ? activation_in[5] : reg_row5_4 ;
//     assign activation_out[6] = test_mode ? activation_in[6] : reg_row6_5 ;
//     assign activation_out[7] = test_mode ? activation_in[7] : reg_row7_6 ;    

// endmodule

tb_Buffer.v
`timescale 1ns / 1ps

module tb_Buffer;

    // 參數定義
    parameter SYSTOLIC_SIZE = 8;
    parameter ACTIVATION_WIDTH = 8;
    parameter CLK_PERIOD = 10;

    // Test signals
    reg clk;
    reg rst_n;
    reg test_mode;
    reg [SYSTOLIC_SIZE*ACTIVATION_WIDTH-1:0] activation_in_flat;
    wire [SYSTOLIC_SIZE*ACTIVATION_WIDTH-1:0] activation_out_flat;

    // Helper signals for testing
    reg [ACTIVATION_WIDTH-1:0] test_data [0:SYSTOLIC_SIZE-1];
    wire [ACTIVATION_WIDTH-1:0] output_data [0:SYSTOLIC_SIZE-1];
    
    // Split output flat signal into array for observation
    genvar k;
    generate
        for (k = 0; k < SYSTOLIC_SIZE; k = k + 1) begin : output_split
            assign output_data[k] = activation_out_flat[k*ACTIVATION_WIDTH +: ACTIVATION_WIDTH];
        end
    endgenerate

    // Instantiate the device under test
    Buffer #(
        .SYSTOLIC_SIZE(SYSTOLIC_SIZE),
        .ACTIVATION_WIDTH(ACTIVATION_WIDTH)
    ) dut (
        .clk(clk),
        .rst_n(rst_n),
        .test_mode(test_mode),
        .activation_in_flat(activation_in_flat),
        .activation_out_flat(activation_out_flat)
    );

    // Clock generation
    initial begin
        clk = 0;
        forever #(CLK_PERIOD/2) clk = ~clk;
    end

    // Task to prepare test data
    task prepare_test_data;
        input [7:0] base_value;
        integer i;
        begin
            for (i = 0; i < SYSTOLIC_SIZE; i = i + 1) begin
                test_data[i] = base_value + i;
            end
            
            // Pack test data into flat signal
            for (i = 0; i < SYSTOLIC_SIZE; i = i + 1) begin
                activation_in_flat[i*ACTIVATION_WIDTH +: ACTIVATION_WIDTH] = test_data[i];
            end
        end
    endtask

    // Task to display output results
    task display_outputs;
        input [255:0] test_name;
        integer i;
        begin
            $display("\n=== %s ===", test_name);
            $display("Time: %0t", $time);
            for (i = 0; i < SYSTOLIC_SIZE; i = i + 1) begin
                $display("Row[%0d]: Input=0x%02h, Output=0x%02h", 
                        i, test_data[i], output_data[i]);
            end
            $display("");
        end
    endtask

    // Task to verify test mode output
    task verify_test_mode;
        integer i;
        reg error_found;
        begin
            error_found = 0;
            $display("=== Verifying Test Mode (Parallel Output) ===");
            for (i = 0; i < SYSTOLIC_SIZE; i = i + 1) begin
                if (output_data[i] !== test_data[i]) begin
                    $display("ERROR: Row[%0d] - Expected: 0x%02h, Got: 0x%02h", 
                            i, test_data[i], output_data[i]);
                    error_found = 1;
                end
            end
            if (!error_found) begin
                $display("PASS: Test mode verification passed");
            end
            $display("");
        end
    endtask

    // Task to verify normal mode delays
    task verify_normal_mode_delays;
        integer i, expected_cycles;
        begin
            $display("=== Verifying Normal Mode Delays ===");
            
            // Row 0 should output immediately
            if (output_data[0] !== test_data[0]) begin
                $display("ERROR: Row[0] - Expected immediate output: 0x%02h, Got: 0x%02h", 
                        test_data[0], output_data[0]);
            end else begin
                $display("PASS: Row[0] immediate output correct");
            end
            
            // Other rows should show delayed data or 0 (if delay time hasn't been reached)
            for (i = 1; i < SYSTOLIC_SIZE; i = i + 1) begin
                $display("Row[%0d]: Output=0x%02h (Delayed by %0d cycles)", 
                        i, output_data[i], i);
            end
            $display("");
        end
    endtask

    // Main test procedure
    initial begin
        // Initialize signals
        rst_n = 0;
        test_mode = 0;
        activation_in_flat = 0;
        
        $display("==========================================");
        $display("Starting Buffer Module Test");
        $display("SYSTOLIC_SIZE = %0d", SYSTOLIC_SIZE);
        $display("ACTIVATION_WIDTH = %0d", ACTIVATION_WIDTH);
        $display("==========================================");

        // Reset
        #(CLK_PERIOD * 2);
        rst_n = 1;
        #(CLK_PERIOD);

        // ===== Test 1: Test Mode (Parallel Output) =====
        $display("\n>>>>> Test 1: Test Mode (Parallel Output) <<<<<");
        test_mode = 1;
        
        // Test data 1
        prepare_test_data(8'h10);
        #(CLK_PERIOD);
        display_outputs("Test Mode - Data Set 1");
        verify_test_mode();
        
        // Test data 2
        prepare_test_data(8'hA0);
        #(CLK_PERIOD);
        display_outputs("Test Mode - Data Set 2");
        verify_test_mode();

        // ===== Test 2: Normal Mode (45-degree Delay) =====
        $display("\n>>>>> Test 2: Normal Mode (45-degree Delay) <<<<<");
        test_mode = 0;
        
        // Reset to clear previous data
        rst_n = 0;
        #(CLK_PERIOD);
        rst_n = 1;
        #(CLK_PERIOD);
        
        // Send first data set
        prepare_test_data(8'h20);
        #(CLK_PERIOD);
        display_outputs("Normal Mode - Cycle 1");
        verify_normal_mode_delays();
        
        // Send second data set
        prepare_test_data(8'h30);
        #(CLK_PERIOD);
        display_outputs("Normal Mode - Cycle 2");
        
        // Send third data set
        prepare_test_data(8'h40);
        #(CLK_PERIOD);
        display_outputs("Normal Mode - Cycle 3");
        
        // Continue for several cycles to observe delay effects
        prepare_test_data(8'h50);
        #(CLK_PERIOD);
        display_outputs("Normal Mode - Cycle 4");
        
        prepare_test_data(8'h60);
        #(CLK_PERIOD);
        display_outputs("Normal Mode - Cycle 5");
        
        prepare_test_data(8'h70);
        #(CLK_PERIOD);
        display_outputs("Normal Mode - Cycle 6");
        
        prepare_test_data(8'h80);
        #(CLK_PERIOD);
        display_outputs("Normal Mode - Cycle 7");
        
        prepare_test_data(8'h90);
        #(CLK_PERIOD);
        display_outputs("Normal Mode - Cycle 8");

        // ===== Test 3: Mode Switching Test =====
        $display("\n>>>>> Test 3: Mode Switching Test <<<<<");
        
        // Switch from normal mode to test mode
        prepare_test_data(8'hF0);
        test_mode = 1;
        #(CLK_PERIOD);
        display_outputs("Mode Switch: Normal->Test");
        verify_test_mode();
        
        // Switch from test mode back to normal mode
        test_mode = 0;
        #(CLK_PERIOD);
        display_outputs("Mode Switch: Test->Normal");

        // ===== Test 4: Reset Test =====
        $display("\n>>>>> Test 4: Reset Function Test <<<<<");
        
        // Reset in normal mode
        test_mode = 0;
        prepare_test_data(8'hCC);
        rst_n = 0;
        #(CLK_PERIOD);
        rst_n = 1;
        #(CLK_PERIOD);
        display_outputs("After Reset - First Cycle");

        // ===== Test 5: Boundary Value Test =====
        $display("\n>>>>> Test 5: Boundary Value Test <<<<<");
        
        test_mode = 1;
        
        // Test all zeros
        prepare_test_data(8'h00);
        #(CLK_PERIOD);
        display_outputs("Boundary Test - All Zeros");
        
        // Test all ones
        prepare_test_data(8'hFF);
        #(CLK_PERIOD);
        display_outputs("Boundary Test - All Ones");

        // ===== Test End =====
        #(CLK_PERIOD * 5);
        $display("\n==========================================");
        $display("Buffer Module Test Complete");
        $display("==========================================");
        
        $finish;
    end

    // Monitor signal changes
    initial begin
        $monitor("Time: %0t | test_mode: %b | rst_n: %b | Input[0]: %02h | Output[0]: %02h", 
                $time, test_mode, rst_n, 
                activation_in_flat[ACTIVATION_WIDTH-1:0], 
                activation_out_flat[ACTIVATION_WIDTH-1:0]);
    end

    // Waveform recording
    initial begin
        $dumpfile("buffer_tb.vcd");
        $dumpvars(0, tb_Buffer);
        
        // Record internal signals for debugging
        $dumpvars(1, dut);
    end

endmodule

Buffer/Buffer/Buffer.sim/sim_1/behav/xsim/tb_buffer.vcd
$date
   Sat Aug  9 05:52:46 2025
$end

$version
  2023.2
  $dumpfile ("tb_buffer.vcd") 
$end

$timescale
  1ps
$end

$scope module tb_Buffer $end
$var reg 1 ! clk $end
$var reg 1 " rst_n $end
$var reg 1 # test_mode $end
$var reg 64 $ activation_in_flat [63:0] $end
$var wire 64 % activation_out_flat [63:0] $end
$upscope $end
$scope module glbl $end
$upscope $end
$enddefinitions $end

#0
$dumpvars
0!
0"
0#
b0 $
b0 %
0&
0'
0(
b0 )
b111 *
bx +
bx ,
bx -
bx .
bx /
x0
bx 1
bx 2
$end

#5000
1!
1&
b111 *

#10000
0!
0&

#15000
1!
1&
b111 *

#20000
0!
1"
0&
1'

#25000
1!
1&
b111 *

#30000
0!
1#
b1011100010110000101010001010000010011000100100001000100010000 $
b1011100010110000101010001010000010011000100100001000100010000 %
0&
1(
b1011100010110000101010001010000010011000100100001000100010000 )
b10000 +
b1000 ,

#35000
1!
1&
b111 *

#40000
0!
b1010011110100110101001011010010010100011101000101010000110100000 $
b1010011110100110101001011010010010100011101000101010000110100000 %
0&
b1010011110100110101001011010010010100011101000101010000110100000 )
b10100000 +
b1000 ,
b11111111111111111111111110111000111111111111111111111111101001101111111111111111111111111110010111111111100011110010000000101101111111111111111111111111101110001111111111111111111111111110011111111111100001000010000000110001 -
b1000 .
b1000 /
00

#45000
1!
1&
b111 *

#50000
0!
0"
0#
b10100000 %
0&
0'
0(
b111 *
b11111111111111111111111110111000111111111111111111111111101001101111111111111111111111111110010111111111100011110010000000101101111111111111111111111111101110001111111111111111111111111110011111111111100001000010000000110010 -
b1000 .
b1000 /

#55000
1!
1&
b111 *

#60000
0!
1"
0&
1'

#65000
1!
b1010000110100000 %
1&
b111 *

#70000
0!
b10011100100110001001010010010000100011001000100010000100100000 $
b1010000100100000 %
0&
b10011100100110001001010010010000100011001000100010000100100000 )
b100000 +
b1000 ,

#75000
1!
b101000100010000100100000 %
1&
b111 *

#80000
0!
b11011100110110001101010011010000110011001100100011000100110000 $
b101000100010000100110000 %
0&
b11011100110110001101010011010000110011001100100011000100110000 )
b110000 +
b1000 ,
b111111111111111111111111101000111111111111111111111111111110011011111111111111111111111110111100100011110010000000101101001000001111111111111111111111111110011011111111100111110010000000110001 -
b1000 .
b1000 1

#85000
1!
b10100011001000100011000100110000 %
1&
b111 *

#90000
0!
b100011101000110010001010100010001000011010000100100000101000000 $
b10100011001000100011000101000000 %
0&
b100011101000110010001010100010001000011010000100100000101000000 )
b1000000 +
b1000 ,
b111111111111111111111111101000111111111111111111111111111110011011111111111111111111111110111100100011110010000000101101001000001111111111111111111111111110011011111111100111110010000000110010 -
b1000 .

#95000
1!
b1010010000100011001100100100000101000000 %
1&
b111 *

#100000
0!
b101011101010110010101010101010001010011010100100101000101010000 $
b1010010000100011001100100100000101010000 %
0&
b101011101010110010101010101010001010011010100100101000101010000 )
b1010000 +
b1000 ,
b111111111111111111111111101000111111111111111111111111111110011011111111111111111111111110111100100011110010000000101101001000001111111111111111111111111110011011111111100111110010000000110011 -
b1000 .

#105000
1!
b101001010010010000110011010000100101000101010000 %
1&
b111 *

#110000
0!
b110011101100110011001010110010001100011011000100110000101100000 $
b101001010010010000110011010000100101000101100000 %
0&
b110011101100110011001010110010001100011011000100110000101100000 )
b1100000 +
b1000 ,
b111111111111111111111111101000111111111111111111111111111110011011111111111111111111111110111100100011110010000000101101001000001111111111111111111111111110011011111111100111110010000000110100 -
b1000 .

#115000
1!
b10100110001001010011010001000011010100100110000101100000 %
1&
b111 *

#120000
0!
b111011101110110011101010111010001110011011100100111000101110000 $
b10100110001001010011010001000011010100100110000101110000 %
0&
b111011101110110011101010111010001110011011100100111000101110000 )
b1110000 +
b1000 ,
b111111111111111111111111101000111111111111111111111111111110011011111111111111111111111110111100100011110010000000101101001000001111111111111111111111111110011011111111100111110010000000110101 -
b1000 .

#125000
1!
b1010011100100110001101010100010001010011011000100111000101110000 %
1&
b111 *

#130000
0!
b1000011110000110100001011000010010000011100000101000000110000000 $
b1010011100100110001101010100010001010011011000100111000110000000 %
0&
b1000011110000110100001011000010010000011100000101000000110000000 )
b10000000 +
b1000 ,
b111111111111111111111111101000111111111111111111111111111110011011111111111111111111111110111100100011110010000000101101001000001111111111111111111111111110011011111111100111110010000000110110 -
b1000 .

#135000
1!
b10011100110110010001010101010001100011011100101000000110000000 %
1&
b111 *

#140000
0!
b1001011110010110100101011001010010010011100100101001000110010000 $
b10011100110110010001010101010001100011011100101000000110010000 %
0&
b1001011110010110100101011001010010010011100100101001000110010000 )
b10010000 +
b1000 ,
b111111111111111111111111101000111111111111111111111111111110011011111111111111111111111110111100100011110010000000101101001000001111111111111111111111111110011011111111100111110010000000110111 -
b1000 .

#145000
1!
b11011101000110010101010110010001110011100000101001000110010000 %
1&
b111 *

#150000
0!
1#
b1111011111110110111101011111010011110011111100101111000111110000 $
b1111011111110110111101011111010011110011111100101111000111110000 %
0&
1(
b1111011111110110111101011111010011110011111100101111000111110000 )
b11110000 +
b1000 ,
b111111111111111111111111101000111111111111111111111111111110011011111111111111111111111110111100100011110010000000101101001000001111111111111111111111111110011011111111100111110010000000111000 -
b1000 .

#155000
1!
1&
b111 *

#160000
0!
0#
b100011101010110011001010111010010000011100100101111000111110000 %
0&
0(
b11111111111111111111111111100101111111111111111111111111100010001111111111111111111111111001101111111111111111111111111110101101111111111111111111111111101110001111111111111111111111111011100011111111111111111111111110100110 -
b1000 .
b1000 /

#165000
1!
b101011101100110011101011000010010010011111100101111000111110000 %
1&
b111 *

#170000
0!
0"
b1101001111010010110100011101000011001111110011101100110111001100 $
b11001100 %
0&
0'
b1101001111010010110100011101000011001111110011101100110111001100 )
b111 *
b11001100 +
b1000 ,
b11111111111111111111111111100101111111111111111111111111100010001111111111111111111111111001101111111111111111111111111110111000111111111111111111111111101001101111111111111111111111111010110111111111111111111111111110111000 -
b1000 .

#175000
1!
1&
b111 *

#180000
0!
1"
0&
1'

#185000
1!
b1100110111001100 %
1&
b111 *

#190000
0!
1#
b11100000110000001010000010000000011000000100000000100000000 $
b11100000110000001010000010000000011000000100000000100000000 %
0&
1(
b11100000110000001010000010000000011000000100000000100000000 )
b0 +
b1000 ,
b111111111111111111111111111001111111111111111111111111111011111010001100001000000010110100100000111111111111111111111111111001001111111111111111111111111000000011111111111111111111111110011111 -
b1000 .

#195000
1!
1&
b111 *

#200000
0!
b11000000101000001000000001100000010000000010000000011111111 $
b11000000101000001000000001100000010000000010000000011111111 %
0&
b11000000101000001000000001100000010000000010000000011111111 )
b11111111 +
b1000 ,
b111111111111111111111111100000101111111111111111111111111000110011111111111111111111111111100110111111111111111111111111101010011010011000100000001011010010000011111111111111111010100000110000 -
b1000 .

#205000
1!
1&
b111 *

#210000
0!
0&
b111111111111111111111111100000101111111111111111111111111000110011111111111111111111111111100110111111111111111111111111101010011010011000100000001011010010000011111111111111111010100000110001 -
b1000 .

#215000
1!
1&
b111 *

#220000
0!
0&

#225000
1!
1&
b111 *

#230000
0!
0&

#235000
1!
1&
b111 *

#240000
0!
0&

#245000
1!
1&
b111 *

#250000
0!
0&

#255000
1!
1&
b111 *
